aws_s3_share/__init__.py
aws_s3_share/cli.py
aws_s3_share/compress.py
aws_s3_share/config.py
aws_s3_share/coordinator.py
aws_s3_share/errors.py
aws_s3_share/progress.py
aws_s3_share/upload.py
aws_s3_share/util.py
aws_s3_share-0.1.3.dist-info/WHEEL
aws_s3_share-0.1.3.dist-info/entry_points.txt
aws_s3_share-0.1.3.dist-info/METADATA
aws_s3_share-0.1.3.dist-info/RECORD
