Metadata-Version: 2.3
Name: aws-s3-share
Version: 0.1.3
Summary: CLI tool for sharing files via Amazon S3 with presigned URLs
Keywords: aws,s3,file-sharing,upload,compression,presigned-url,cli
Author: Dennis Conrad
Author-email: Dennis Conrad <dennis.conrad@cloudinental.com>
License:                                  Apache License
Classifier: Development Status :: 4 - Beta
Classifier: Environment :: Console
Classifier: Intended Audience :: Developers
Classifier: Intended Audience :: System Administrators
Classifier: License :: OSI Approved :: Apache Software License
Classifier: Operating System :: OS Independent
Classifier: Programming Language :: Python :: 3
Classifier: Programming Language :: Python :: 3.10
Classifier: Programming Language :: Python :: 3.11
Classifier: Programming Language :: Python :: 3.12
Classifier: Programming Language :: Python :: 3.13
Classifier: Topic :: Communications :: File Sharing
Classifier: Topic :: System :: Archiving :: Compression
Classifier: Topic :: Utilities
Requires-Dist: boto3>=1.38.32
Requires-Dist: click>=8.2.1
Requires-Dist: pipx>=1.7.1
Requires-Dist: tomli>=2.2.1 ; python_full_version < '3.11'
Requires-Python: >=3.10
Project-URL: Documentation, https://github.com/dennisconrad/aws-s3-share#readme
Project-URL: Homepage, https://github.com/dennisconrad/aws-s3-share
Project-URL: Issues, https://github.com/dennisconrad/aws-s3-share/issues
Project-URL: Source, https://github.com/dennisconrad/aws-s3-share
